{
  "greetings": {
    "casual": {
      "casual1": {
        "patterns": [
          "czesc",
          "hej",
          "hejka",
          "siema",
          "siemka"
        ],
        "mining": [
          "greetings",
          "casual",
          "positive"
        ]
      },
      "casual2": {
        "patterns": [
          "siemandero",
          "siemaneczko",
          "siemano",
          "siemasz"
        ],
        "mining": [
          "greetings",
          "casual",
          "weird"
        ]
      }
    }
  },
  "questions": {
    "questions-to-the-bot": {
      "personal1": {
        "patterns": [
          "kimjestes"
        ],
        "mining": [
          "questions",
          "questions-to-the-bot",
          "personal",
          "positive",
          "kimjestes"
        ]
      },
      "personal2": {
        "patterns": [
          "cotam"
        ],
        "mining": [
          "questions",
          "questions-to-the-bot",
          "personal",
          "positive",
          "cotam"
        ]
      },
      "personal3": {
        "patterns": [
          "czymjestes"
        ],
        "mining": [
          "questions",
          "questions-to-the-bot",
          "personal",
          "pejorative",
          "czymjestes"
        ]
      },
      "skills1": {
        "patterns": [
          "copotrafisz"
        ],
        "mining": [
          "questions",
          "questions-to-the-bot",
          "skills",
          "copotrafisz"
        ]
      }
    },
    "words-that-identify-a-sentence-as-a-question": {
      "basic": {
        "pattern": [
          "czy"
        ],
        "mining": [
          "question",
          "basic",
          "obvious-meaning"
        ]
      }
    }
  },
  "questions-for-the-bot-requiring-action": {
    "basic": {
      "what-time": {
        "pattern": [
          "jakajestgodzina",
          "jakajestterazgodzina",
          "którajestterazgodzina"
        ],
        "mining": [
          "bot-action",
          "questions-for-the-bot-requiring-action",
          "basic",
          "what-time"
        ]
      }
    }
  }
}